{"name":"Descargas","tagline":"Repositorio de Descargas","body":"### Bienvenido al Menu de Casa-Julian interactivo.\r\nEn esta pagina podras descargar el menu de Casa-Julian de forma interactiva.\r\n\r\n### Plataformas\r\nDe momento solo esta disponible la version para 3DS y para PC. Estará disponible para Android,IOS,Mac OS,Linux,PSP,WII y Raspberry\r\n\r\n### 3DS\r\nPuedes descargar la version en construccion para probar este servicio\r\nEn la pagina de releases de el proyecto : https://github.com/Casa-Julian/Casa-Julian-3DS/releases\r\n\r\n### Autores\r\nCasa Julian\r\n\r\n### Soporte y contacto\r\nwww.casa-julian.es\r\nPodras ver todos los menus,noticias y el contacto.","google":"","note":"Don't delete this file! It's used internally to help with page regeneration."}